evil_insult/__init__.py
evil_insult/__main__.py
evil_insult/api.py
evil_insult-0.0.1.dist-info/METADATA
evil_insult-0.0.1.dist-info/WHEEL
evil_insult-0.0.1.dist-info/top_level.txt
evil_insult-0.0.1.dist-info/RECORD
